tests/__init__.py
tests/lmm.py
tests/test_data.py
tests/test_metric.py
tests/test_net.py
tests/test_out.py
tests/test_util.py
tests/test_vi.py
tests/test_warning.py
tests/util.py
wbml/__init__.py
wbml/_version.py
wbml/experiment.py
wbml/metric.py
wbml/net.py
wbml/out.py
wbml/parser.py
wbml/plot.py
wbml/util.py
wbml/vi.py
wbml/warning.py
wbml/data/__init__.py
wbml/data/air_temp.py
wbml/data/cmip5.py
wbml/data/crude_oil.py
wbml/data/data.py
wbml/data/eeg.py
wbml/data/exchange.py
wbml/data/jura.py
wbml/data/kemar.py
wbml/data/mauna_loa.py
wbml/data/mf_temp.py
wbml/data/miso.py
wbml/data/predprey.py
wbml/data/snp.py
wbml/data/station.py
wbml/data/toy_sines.py
wbml/data/vix.py
wbml-0.4.2.dist-info/LICENCE.txt
wbml-0.4.2.dist-info/METADATA
wbml-0.4.2.dist-info/WHEEL
wbml-0.4.2.dist-info/top_level.txt
wbml-0.4.2.dist-info/RECORD
