Metadata-Version: 2.1
Name: wbml
Version: 0.4.2
Summary: Machine learning stuff
Home-page: https://github.com/wesselb/wbml
Author: Wessel Bruinsma
Author-email: wessel.p.bruinsma@gmail.com
License: MIT
Requires-Python: >=3.6
License-File: LICENCE.txt
Requires-Dist: six
Requires-Dist: numpy>=1.16
Requires-Dist: pandas
Requires-Dist: pyarrow
Requires-Dist: python-slugify
Requires-Dist: requests
Requires-Dist: netCDF4
Requires-Dist: scikit-learn
Requires-Dist: matplotlib
Requires-Dist: xarray
Requires-Dist: plum-dispatch>=2
Requires-Dist: backends>=1
Requires-Dist: backends-matrix>=1
Requires-Dist: stheno>=1.4.2
Requires-Dist: varz>=0.6
